mimicdb
tests
