Metadata-Version: 1.0
Name: MimicDB
Version: 1.0.5
Summary: Python implementation of MimicDB
Home-page: https://github.com/nathancahill/mimicdb
Author: Nathan Cahill
Author-email: nathan@nathancahill.com
License: BSD
Platform: UNKNOWN
